antspyt1w/__init__.py
antspyt1w/get_data.py
antspyt1w-1.1.3.dist-info/METADATA
antspyt1w-1.1.3.dist-info/WHEEL
antspyt1w-1.1.3.dist-info/top_level.txt
antspyt1w-1.1.3.dist-info/RECORD
