Metadata-Version: 2.4
Name: antspyt1w
Version: 1.1.3
Summary: T1w human neuroimage processing with antspyx
Author-email: "Avants, Gosselin, Tustison" <stnava@gmail.com>
License:                                  Apache License
Project-URL: homepage, https://github.com/stnava/ANTsPyT1w
Classifier: License :: OSI Approved :: Apache Software License
Classifier: Programming Language :: Python :: 3
Classifier: Operating System :: OS Independent
Requires-Python: >=3.7
Requires-Dist: h5py>=3.10.0
Requires-Dist: numpy>=1.19.4
Requires-Dist: pandas>=1.0.1
Requires-Dist: antspyx>=0.6.1
Requires-Dist: antspynet>=0.2.9
Requires-Dist: tensorflow-probability>=0.22.0
Requires-Dist: tensorflow>=2.11.0
Requires-Dist: pathlib
Requires-Dist: PyNomaly>=0.3.3
Requires-Dist: pytest>=8.0.1
Requires-Dist: scipy
Requires-Dist: pillow
Requires-Dist: matplotlib
